astar_wxpaysdk/__init__.py
astar_wxpaysdk/account.py
astar_wxpaysdk/common.py
astar_wxpaysdk/pay.py
astar_wxpaysdk/util.py
astar_wxpaysdk-0.0.1.dist-info/DESCRIPTION.rst
astar_wxpaysdk-0.0.1.dist-info/METADATA
astar_wxpaysdk-0.0.1.dist-info/RECORD
astar_wxpaysdk-0.0.1.dist-info/WHEEL
astar_wxpaysdk-0.0.1.dist-info/metadata.json
astar_wxpaysdk-0.0.1.dist-info/top_level.txt
