Metadata-Version: 2.0
Name: astar-wxpaysdk
Version: 0.0.1
Summary: toolkit for wechat pay
Home-page: http://182.61.50.242:10010/python/astar-wxpay-python
Author: A.Star
Author-email: astar@snowland.ltd
License: Apache v2.0
Platform: all
Classifier: Operating System :: OS Independent
Classifier: Intended Audience :: Developers
Classifier: Programming Language :: Python
Classifier: Programming Language :: Python :: Implementation
Classifier: Programming Language :: Python :: 3
Classifier: Programming Language :: Python :: 3.6
Classifier: Programming Language :: Python :: 3.7
Classifier: Topic :: Software Development :: Libraries
Requires-Dist: astartool (>=0.0.2)
Requires-Dist: requests
Requires-Dist: snowland-smx (>=0.3.1)
Requires-Dist: beautifulsoup4
